{
  "_format": "hh-sol-cache-2",
  "files": {
    "/home/abdulazeez/Github/meme/contracts/Erc20.sol": {
      "lastModificationDate": 1729448422671,
      "contentHash": "2fcadd5b66f5256e3d2df9cc27001335",
      "sourceName": "contracts/Erc20.sol",
      "solcConfig": {
        "version": "0.8.27",
        "settings": {
          "evmVersion": "paris",
          "optimizer": {
            "enabled": false,
            "runs": 200
          },
          "outputSelection": {
            "*": {
              "*": [
                "abi",
                "evm.bytecode",
                "evm.deployedBytecode",
                "evm.methodIdentifiers",
                "metadata"
              ],
              "": [
                "ast"
              ]
            }
          }
        }
      },
      "imports": [
        "@openzeppelin/contracts/access/Ownable.sol"
      ],
      "versionPragmas": [
        "^0.8.0"
      ],
      "artifacts": [
        "ERC20"
      ]
    },
    "/home/abdulazeez/Github/meme/contracts/TokenFactory.sol": {
      "lastModificationDate": 1729448582831,
      "contentHash": "275d931596ef8fddc488286af1bcf836",
      "sourceName": "contracts/TokenFactory.sol",
      "solcConfig": {
        "version": "0.8.27",
        "settings": {
          "evmVersion": "paris",
          "optimizer": {
            "enabled": false,
            "runs": 200
          },
          "outputSelection": {
            "*": {
              "*": [
                "abi",
                "evm.bytecode",
                "evm.deployedBytecode",
                "evm.methodIdentifiers",
                "metadata"
              ],
              "": [
                "ast"
              ]
            }
          }
        }
      },
      "imports": [
        "@openzeppelin/contracts/access/Ownable.sol",
        "@openzeppelin/contracts/utils/ReentrancyGuard.sol",
        "./Erc20.sol"
      ],
      "versionPragmas": [
        "^0.8.27"
      ],
      "artifacts": [
        "TokenFactory"
      ]
    },
    "/home/abdulazeez/Github/meme/node_modules/@openzeppelin/contracts/access/Ownable.sol": {
      "lastModificationDate": 1729025378453,
      "contentHash": "d3c790edc9ccf808a17c5a6cd13614fd",
      "sourceName": "@openzeppelin/contracts/access/Ownable.sol",
      "solcConfig": {
        "version": "0.8.27",
        "settings": {
          "evmVersion": "paris",
          "optimizer": {
            "enabled": false,
            "runs": 200
          },
          "outputSelection": {
            "*": {
              "*": [
                "abi",
                "evm.bytecode",
                "evm.deployedBytecode",
                "evm.methodIdentifiers",
                "metadata"
              ],
              "": [
                "ast"
              ]
            }
          }
        }
      },
      "imports": [
        "../utils/Context.sol"
      ],
      "versionPragmas": [
        "^0.8.20"
      ],
      "artifacts": [
        "Ownable"
      ]
    },
    "/home/abdulazeez/Github/meme/node_modules/@openzeppelin/contracts/utils/Context.sol": {
      "lastModificationDate": 1729025378453,
      "contentHash": "67bfbc07588eb8683b3fd8f6f909563e",
      "sourceName": "@openzeppelin/contracts/utils/Context.sol",
      "solcConfig": {
        "version": "0.8.27",
        "settings": {
          "evmVersion": "paris",
          "optimizer": {
            "enabled": false,
            "runs": 200
          },
          "outputSelection": {
            "*": {
              "*": [
                "abi",
                "evm.bytecode",
                "evm.deployedBytecode",
                "evm.methodIdentifiers",
                "metadata"
              ],
              "": [
                "ast"
              ]
            }
          }
        }
      },
      "imports": [],
      "versionPragmas": [
        "^0.8.20"
      ],
      "artifacts": [
        "Context"
      ]
    },
    "/home/abdulazeez/Github/meme/node_modules/@openzeppelin/contracts/utils/ReentrancyGuard.sol": {
      "lastModificationDate": 1729447504431,
      "contentHash": "a92331adac11b453a4de0323fc948119",
      "sourceName": "@openzeppelin/contracts/utils/ReentrancyGuard.sol",
      "solcConfig": {
        "version": "0.8.27",
        "settings": {
          "evmVersion": "paris",
          "optimizer": {
            "enabled": false,
            "runs": 200
          },
          "outputSelection": {
            "*": {
              "*": [
                "abi",
                "evm.bytecode",
                "evm.deployedBytecode",
                "evm.methodIdentifiers",
                "metadata"
              ],
              "": [
                "ast"
              ]
            }
          }
        }
      },
      "imports": [],
      "versionPragmas": [
        "^0.8.20"
      ],
      "artifacts": [
        "ReentrancyGuard"
      ]
    }
  }
}
